codonbias/__init__.py
codonbias/genetic_code_ncbi.csv
codonbias/optimizers.py
codonbias/pairwise.py
codonbias/random.py
codonbias/scores.py
codonbias/stats.py
codonbias/tAI_svalues_Tuller.csv
codonbias/tAI_svalues_dosReis.csv
codonbias/utils.py
codon_bias-0.3.5.dist-info/LICENSE
codon_bias-0.3.5.dist-info/METADATA
codon_bias-0.3.5.dist-info/WHEEL
codon_bias-0.3.5.dist-info/top_level.txt
codon_bias-0.3.5.dist-info/RECORD
