Metadata-Version: 2.1
Name: codon-bias
Version: 0.3.5
Summary: codon usage bias analysis tools
Home-page: https://github.com/alondmnt/codon-bias
Author: Alon Diament
Author-email: dev@alondmnt.com
License: MIT
Project-URL: Documentation, https://codon-bias.readthedocs.io/en/latest/
Classifier: Intended Audience :: Science/Research
Classifier: License :: OSI Approved :: MIT License
Classifier: Programming Language :: Python :: 3
Classifier: Programming Language :: Python :: 3.8
Classifier: Programming Language :: Python :: 3.9
Classifier: Programming Language :: Python :: 3.10
Classifier: Programming Language :: Python :: 3.11
Classifier: Programming Language :: Python :: 3.12
Classifier: Programming Language :: Python :: 3.13
Requires-Python: >=3
License-File: LICENSE
Requires-Dist: numpy
Requires-Dist: scipy
Requires-Dist: pandas
Requires-Dist: pandarallel
